[
  {
    "symbol": "AAVEUSDT",
    "fundingTime": 1751644800001,
    "fundingRate": "0.00003133",
    "markPrice": "261.73939062"
  },
  {
    "symbol": "AAVEUSDT",
    "fundingTime": 1751673600004,
    "fundingRate": "-0.00005838",
    "markPrice": "265.84000000"
  },
  {
    "symbol": "AAVEUSDT",
    "fundingTime": 1751702400009,
    "fundingRate": "0.00002584",
    "markPrice": "270.31693229"
  },
  {
    "symbol": "AAVEUSDT",
    "fundingTime": 1751731200006,
    "fundingRate": "0.00010000",
    "markPrice": "269.96000000"
  },
  {
    "symbol": "AAVEUSDT",
    "fundingTime": 1751760000001,
    "fundingRate": "0.00010000",
    "markPrice": "273.38924479"
  },
  {
    "symbol": "AAVEUSDT",
    "fundingTime": 1751788800002,
    "fundingRate": "0.00008730",
    "markPrice": "271.28827083"
  },
  {
    "symbol": "AAVEUSDT",
    "fundingTime": 1751817600004,
    "fundingRate": "0.00007607",
    "markPrice": "275.95000000"
  },
  {
    "symbol": "AAVEUSDT",
    "fundingTime": 1751846400000,
    "fundingRate": "0.00010000",
    "markPrice": "287.26203646"
  },
  {
    "symbol": "AAVEUSDT",
    "fundingTime": 1751875200007,
    "fundingRate": "0.00010000",
    "markPrice": "287.15000000"
  },
  {
    "symbol": "AAVEUSDT",
    "fundingTime": 1751904000000,
    "fundingRate": "0.00010000",
    "markPrice": "286.53000000"
  },
  {
    "symbol": "AAVEUSDT",
    "fundingTime": 1751932800010,
    "fundingRate": "0.00003154",
    "markPrice": "283.00000000"
  },
  {
    "symbol": "AAVEUSDT",
    "fundingTime": 1751961600003,
    "fundingRate": "0.00003042",
    "markPrice": "282.81978646"
  },
  {
    "symbol": "AAVEUSDT",
    "fundingTime": 1751990400000,
    "fundingRate": "0.00010000",
    "markPrice": "285.33000000"
  },
  {
    "symbol": "AAVEUSDT",
    "fundingTime": 1752019200002,
    "fundingRate": "0.00009813",
    "markPrice": "292.85000000"
  },
  {
    "symbol": "AAVEUSDT",
    "fundingTime": 1752048000006,
    "fundingRate": "0.00006743",
    "markPrice": "298.79000000"
  },
  {
    "symbol": "AAVEUSDT",
    "fundingTime": 1752076800001,
    "fundingRate": "0.00009886",
    "markPrice": "297.89000000"
  },
  {
    "symbol": "AAVEUSDT",
    "fundingTime": 1752105600003,
    "fundingRate": "0.00009075",
    "markPrice": "301.47000000"
  },
  {
    "symbol": "AAVEUSDT",
    "fundingTime": 1752134400000,
    "fundingRate": "0.00001636",
    "markPrice": "297.14000000"
  },
  {
    "symbol": "AAVEUSDT",
    "fundingTime": 1752163200004,
    "fundingRate": "0.00002464",
    "markPrice": "295.97000000"
  },
  {
    "symbol": "AAVEUSDT",
    "fundingTime": 1752192000004,
    "fundingRate": "0.00010000",
    "markPrice": "308.69221354"
  },
  {
    "symbol": "AAVEUSDT",
    "fundingTime": 1752220800007,
    "fundingRate": "0.00010000",
    "markPrice": "308.30918229"
  },
  {
    "symbol": "AAVEUSDT",
    "fundingTime": 1752249600001,
    "fundingRate": "0.00010000",
    "markPrice": "304.47406250"
  },
  {
    "symbol": "AAVEUSDT",
    "fundingTime": 1752278400000,
    "fundingRate": "0.00010000",
    "markPrice": "297.37115625"
  },
  {
    "symbol": "AAVEUSDT",
    "fundingTime": 1752307200001,
    "fundingRate": "0.00010000",
    "markPrice": "301.96000000"
  },
  {
    "symbol": "AAVEUSDT",
    "fundingTime": 1752336000002,
    "fundingRate": "0.00010000",
    "markPrice": "295.51000000"
  },
  {
    "symbol": "AAVEUSDT",
    "fundingTime": 1752364800006,
    "fundingRate": "0.00010000",
    "markPrice": "302.14593750"
  },
  {
    "symbol": "AAVEUSDT",
    "fundingTime": 1752393600001,
    "fundingRate": "0.00010000",
    "markPrice": "304.51212500"
  },
  {
    "symbol": "AAVEUSDT",
    "fundingTime": 1752422400003,
    "fundingRate": "0.00010000",
    "markPrice": "311.51616918"
  },
  {
    "symbol": "AAVEUSDT",
    "fundingTime": 1752451200000,
    "fundingRate": "0.00010000",
    "markPrice": "305.60100000"
  },
  {
    "symbol": "AAVEUSDT",
    "fundingTime": 1752480000000,
    "fundingRate": "0.00010000",
    "markPrice": "324.36000000"
  },
  {
    "symbol": "AAVEUSDT",
    "fundingTime": 1752508800000,
    "fundingRate": "0.00010000",
    "markPrice": "319.95437500"
  },
  {
    "symbol": "AAVEUSDT",
    "fundingTime": 1752537600002,
    "fundingRate": "0.00010000",
    "markPrice": "315.05490625"
  },
  {
    "symbol": "AAVEUSDT",
    "fundingTime": 1752566400000,
    "fundingRate": "0.00010000",
    "markPrice": "313.44000000"
  },
  {
    "symbol": "AAVEUSDT",
    "fundingTime": 1752595200000,
    "fundingRate": "0.00010000",
    "markPrice": "323.31656250"
  },
  {
    "symbol": "AAVEUSDT",
    "fundingTime": 1752624000000,
    "fundingRate": "0.00010000",
    "markPrice": "327.50000000"
  },
  {
    "symbol": "AAVEUSDT",
    "fundingTime": 1752652800000,
    "fundingRate": "0.00010000",
    "markPrice": "332.60232812"
  },
  {
    "symbol": "AAVEUSDT",
    "fundingTime": 1752681600008,
    "fundingRate": "0.00010000",
    "markPrice": "326.46000000"
  },
  {
    "symbol": "AAVEUSDT",
    "fundingTime": 1752710400003,
    "fundingRate": "0.00010000",
    "markPrice": "323.17000000"
  },
  {
    "symbol": "AAVEUSDT",
    "fundingTime": 1752739200000,
    "fundingRate": "0.00010000",
    "markPrice": "324.30000000"
  },
  {
    "symbol": "AAVEUSDT",
    "fundingTime": 1752768000000,
    "fundingRate": "0.00010000",
    "markPrice": "324.56000000"
  },
  {
    "symbol": "AAVEUSDT",
    "fundingTime": 1752796800004,
    "fundingRate": "0.00010000",
    "markPrice": "321.62310938"
  },
  {
    "symbol": "AAVEUSDT",
    "fundingTime": 1752825600000,
    "fundingRate": "0.00010000",
    "markPrice": "327.70000000"
  },
  {
    "symbol": "AAVEUSDT",
    "fundingTime": 1752854400000,
    "fundingRate": "0.00010000",
    "markPrice": "317.54906250"
  },
  {
    "symbol": "AAVEUSDT",
    "fundingTime": 1752883200009,
    "fundingRate": "0.00010000",
    "markPrice": "324.35000000"
  },
  {
    "symbol": "AAVEUSDT",
    "fundingTime": 1752912000000,
    "fundingRate": "0.00010000",
    "markPrice": "316.34000000"
  },
  {
    "symbol": "AAVEUSDT",
    "fundingTime": 1752940800002,
    "fundingRate": "0.00010000",
    "markPrice": "315.41090625"
  },
  {
    "symbol": "AAVEUSDT",
    "fundingTime": 1752969600000,
    "fundingRate": "0.00010000",
    "markPrice": "319.14000000"
  },
  {
    "symbol": "AAVEUSDT",
    "fundingTime": 1752998400000,
    "fundingRate": "0.00010000",
    "markPrice": "325.78507812"
  },
  {
    "symbol": "AAVEUSDT",
    "fundingTime": 1753027200000,
    "fundingRate": "0.00010000",
    "markPrice": "333.85000000"
  },
  {
    "symbol": "AAVEUSDT",
    "fundingTime": 1753056000001,
    "fundingRate": "0.00010000",
    "markPrice": "324.34000000"
  },
  {
    "symbol": "AAVEUSDT",
    "fundingTime": 1753084800000,
    "fundingRate": "0.00010000",
    "markPrice": "330.45666667"
  },
  {
    "symbol": "AAVEUSDT",
    "fundingTime": 1753113600001,
    "fundingRate": "0.00010000",
    "markPrice": "327.00000000"
  },
  {
    "symbol": "AAVEUSDT",
    "fundingTime": 1753142400000,
    "fundingRate": "0.00010000",
    "markPrice": "322.14000000"
  },
  {
    "symbol": "AAVEUSDT",
    "fundingTime": 1753171200010,
    "fundingRate": "0.00010000",
    "markPrice": "309.54642188"
  },
  {
    "symbol": "AAVEUSDT",
    "fundingTime": 1753200000007,
    "fundingRate": "0.00010000",
    "markPrice": "307.12000000"
  },
  {
    "symbol": "AAVEUSDT",
    "fundingTime": 1753228800000,
    "fundingRate": "0.00010000",
    "markPrice": "310.54781250"
  },
  {
    "symbol": "AAVEUSDT",
    "fundingTime": 1753257600004,
    "fundingRate": "0.00010000",
    "markPrice": "301.75425521"
  },
  {
    "symbol": "AAVEUSDT",
    "fundingTime": 1753286400002,
    "fundingRate": "0.00010000",
    "markPrice": "293.92874479"
  },
  {
    "symbol": "AAVEUSDT",
    "fundingTime": 1753315200000,
    "fundingRate": "0.00007321",
    "markPrice": "290.22000000"
  },
  {
    "symbol": "AAVEUSDT",
    "fundingTime": 1753344000001,
    "fundingRate": "0.00009261",
    "markPrice": "284.82616146"
  },
  {
    "symbol": "AAVEUSDT",
    "fundingTime": 1753372800000,
    "fundingRate": "0.00003765",
    "markPrice": "290.99000000"
  },
  {
    "symbol": "AAVEUSDT",
    "fundingTime": 1753401600000,
    "fundingRate": "-0.00000245",
    "markPrice": "285.97000000"
  },
  {
    "symbol": "AAVEUSDT",
    "fundingTime": 1753430400000,
    "fundingRate": "0.00005416",
    "markPrice": "285.86531250"
  },
  {
    "symbol": "AAVEUSDT",
    "fundingTime": 1753459200000,
    "fundingRate": "0.00006780",
    "markPrice": "288.34000000"
  },
  {
    "symbol": "AAVEUSDT",
    "fundingTime": 1753488000001,
    "fundingRate": "0.00010000",
    "markPrice": "294.01995233"
  },
  {
    "symbol": "AAVEUSDT",
    "fundingTime": 1753516800005,
    "fundingRate": "0.00010000",
    "markPrice": "295.92000000"
  },
  {
    "symbol": "AAVEUSDT",
    "fundingTime": 1753545600001,
    "fundingRate": "0.00010000",
    "markPrice": "294.83000000"
  },
  {
    "symbol": "AAVEUSDT",
    "fundingTime": 1753574400001,
    "fundingRate": "0.00010000",
    "markPrice": "294.84000000"
  },
  {
    "symbol": "AAVEUSDT",
    "fundingTime": 1753603200000,
    "fundingRate": "0.00010000",
    "markPrice": "295.80694792"
  },
  {
    "symbol": "AAVEUSDT",
    "fundingTime": 1753632000008,
    "fundingRate": "0.00000656",
    "markPrice": "296.90543750"
  },
  {
    "symbol": "AAVEUSDT",
    "fundingTime": 1753660800005,
    "fundingRate": "0.00010000",
    "markPrice": "304.77000000"
  },
  {
    "symbol": "AAVEUSDT",
    "fundingTime": 1753689600000,
    "fundingRate": "0.00009457",
    "markPrice": "305.87000000"
  },
  {
    "symbol": "AAVEUSDT",
    "fundingTime": 1753718400000,
    "fundingRate": "0.00010000",
    "markPrice": "292.00747917"
  },
  {
    "symbol": "AAVEUSDT",
    "fundingTime": 1753747200001,
    "fundingRate": "0.00005942",
    "markPrice": "288.82065104"
  },
  {
    "symbol": "AAVEUSDT",
    "fundingTime": 1753776000000,
    "fundingRate": "0.00007007",
    "markPrice": "295.27000000"
  },
  {
    "symbol": "AAVEUSDT",
    "fundingTime": 1753804800000,
    "fundingRate": "0.00004318",
    "markPrice": "282.60522917"
  },
  {
    "symbol": "AAVEUSDT",
    "fundingTime": 1753833600011,
    "fundingRate": "0.00003353",
    "markPrice": "282.23000000"
  },
  {
    "symbol": "AAVEUSDT",
    "fundingTime": 1753862400000,
    "fundingRate": "-0.00001150",
    "markPrice": "281.69573958"
  },
  {
    "symbol": "AAVEUSDT",
    "fundingTime": 1753891200008,
    "fundingRate": "0.00002147",
    "markPrice": "276.10000000"
  },
  {
    "symbol": "AAVEUSDT",
    "fundingTime": 1753920000000,
    "fundingRate": "0.00009551",
    "markPrice": "274.51000000"
  },
  {
    "symbol": "AAVEUSDT",
    "fundingTime": 1753948800009,
    "fundingRate": "0.00002928",
    "markPrice": "277.57000000"
  },
  {
    "symbol": "AAVEUSDT",
    "fundingTime": 1753977600000,
    "fundingRate": "-0.00004012",
    "markPrice": "268.69000000"
  },
  {
    "symbol": "AAVEUSDT",
    "fundingTime": 1754006400001,
    "fundingRate": "0.00010000",
    "markPrice": "260.88000000"
  },
  {
    "symbol": "AAVEUSDT",
    "fundingTime": 1754035200003,
    "fundingRate": "0.00002193",
    "markPrice": "258.13000000"
  },
  {
    "symbol": "AAVEUSDT",
    "fundingTime": 1754064000000,
    "fundingRate": "0.00006728",
    "markPrice": "259.38579688"
  },
  {
    "symbol": "AAVEUSDT",
    "fundingTime": 1754092800004,
    "fundingRate": "0.00010000",
    "markPrice": "255.30295312"
  },
  {
    "symbol": "AAVEUSDT",
    "fundingTime": 1754121600000,
    "fundingRate": "0.00008224",
    "markPrice": "255.55000000"
  },
  {
    "symbol": "AAVEUSDT",
    "fundingTime": 1754150400000,
    "fundingRate": "0.00007093",
    "markPrice": "251.92000000"
  },
  {
    "symbol": "AAVEUSDT",
    "fundingTime": 1754179200000,
    "fundingRate": "0.00004994",
    "markPrice": "249.33000000"
  },
  {
    "symbol": "AAVEUSDT",
    "fundingTime": 1754208000000,
    "fundingRate": "-0.00000898",
    "markPrice": "255.77643750"
  },
  {
    "symbol": "AAVEUSDT",
    "fundingTime": 1754236800003,
    "fundingRate": "0.00001754",
    "markPrice": "257.44271875"
  },
  {
    "symbol": "AAVEUSDT",
    "fundingTime": 1754265600004,
    "fundingRate": "0.00001830",
    "markPrice": "259.90445312"
  },
  {
    "symbol": "AAVEUSDT",
    "fundingTime": 1754294400000,
    "fundingRate": "0.00006852",
    "markPrice": "261.61000000"
  },
  {
    "symbol": "AAVEUSDT",
    "fundingTime": 1754323200002,
    "fundingRate": "-0.00001555",
    "markPrice": "265.28785417"
  },
  {
    "symbol": "AAVEUSDT",
    "fundingTime": 1754352000000,
    "fundingRate": "0.00008768",
    "markPrice": "267.73719792"
  },
  {
    "symbol": "AAVEUSDT",
    "fundingTime": 1754380800000,
    "fundingRate": "0.00010000",
    "markPrice": "257.27975000"
  },
  {
    "symbol": "AAVEUSDT",
    "fundingTime": 1754409600000,
    "fundingRate": "0.00009938",
    "markPrice": "253.75933854"
  },
  {
    "symbol": "AAVEUSDT",
    "fundingTime": 1754438400005,
    "fundingRate": "0.00008058",
    "markPrice": "255.26272917"
  },
  {
    "symbol": "AAVEUSDT",
    "fundingTime": 1754467200000,
    "fundingRate": "0.00004779",
    "markPrice": "258.44000000"
  },
  {
    "symbol": "AAVEUSDT",
    "fundingTime": 1754496000000,
    "fundingRate": "0.00004255",
    "markPrice": "262.93481250"
  },
  {
    "symbol": "AAVEUSDT",
    "fundingTime": 1754524800003,
    "fundingRate": "0.00010000",
    "markPrice": "263.43629167"
  },
  {
    "symbol": "AAVEUSDT",
    "fundingTime": 1754553600002,
    "fundingRate": "0.00010000",
    "markPrice": "265.83000000"
  },
  {
    "symbol": "AAVEUSDT",
    "fundingTime": 1754582400002,
    "fundingRate": "0.00004519",
    "markPrice": "273.17447917"
  },
  {
    "symbol": "AAVEUSDT",
    "fundingTime": 1754611200002,
    "fundingRate": "0.00009654",
    "markPrice": "284.99398305"
  },
  {
    "symbol": "AAVEUSDT",
    "fundingTime": 1754640000004,
    "fundingRate": "0.00009684",
    "markPrice": "283.36000000"
  },
  {
    "symbol": "AAVEUSDT",
    "fundingTime": 1754668800000,
    "fundingRate": "0.00004617",
    "markPrice": "283.85332051"
  },
  {
    "symbol": "AAVEUSDT",
    "fundingTime": 1754697600005,
    "fundingRate": "0.00005094",
    "markPrice": "290.82000000"
  },
  {
    "symbol": "AAVEUSDT",
    "fundingTime": 1754726400000,
    "fundingRate": "0.00010000",
    "markPrice": "299.47000000"
  },
  {
    "symbol": "AAVEUSDT",
    "fundingTime": 1754755200007,
    "fundingRate": "0.00010000",
    "markPrice": "302.64589103"
  },
  {
    "symbol": "AAVEUSDT",
    "fundingTime": 1754784000003,
    "fundingRate": "0.00010000",
    "markPrice": "307.69000000"
  },
  {
    "symbol": "AAVEUSDT",
    "fundingTime": 1754812800005,
    "fundingRate": "0.00010000",
    "markPrice": "300.15192308"
  },
  {
    "symbol": "AAVEUSDT",
    "fundingTime": 1754841600002,
    "fundingRate": "0.00010000",
    "markPrice": "307.73154487"
  },
  {
    "symbol": "AAVEUSDT",
    "fundingTime": 1754870400000,
    "fundingRate": "0.00010000",
    "markPrice": "306.14986538"
  },
  {
    "symbol": "AAVEUSDT",
    "fundingTime": 1754899200000,
    "fundingRate": "0.00010000",
    "markPrice": "305.18073438"
  },
  {
    "symbol": "AAVEUSDT",
    "fundingTime": 1754928000000,
    "fundingRate": "0.00008271",
    "markPrice": "298.45000000"
  },
  {
    "symbol": "AAVEUSDT",
    "fundingTime": 1754956800000,
    "fundingRate": "0.00010000",
    "markPrice": "293.04021875"
  },
  {
    "symbol": "AAVEUSDT",
    "fundingTime": 1754985600001,
    "fundingRate": "-0.00003746",
    "markPrice": "297.60000000"
  },
  {
    "symbol": "AAVEUSDT",
    "fundingTime": 1755014400005,
    "fundingRate": "0.00005201",
    "markPrice": "313.24875000"
  },
  {
    "symbol": "AAVEUSDT",
    "fundingTime": 1755043200000,
    "fundingRate": "0.00010000",
    "markPrice": "322.20000000"
  },
  {
    "symbol": "AAVEUSDT",
    "fundingTime": 1755072000002,
    "fundingRate": "0.00010000",
    "markPrice": "322.98438542"
  },
  {
    "symbol": "AAVEUSDT",
    "fundingTime": 1755100800006,
    "fundingRate": "0.00010000",
    "markPrice": "323.27985417"
  },
  {
    "symbol": "AAVEUSDT",
    "fundingTime": 1755129600002,
    "fundingRate": "0.00010000",
    "markPrice": "332.19687500"
  },
  {
    "symbol": "AAVEUSDT",
    "fundingTime": 1755158400003,
    "fundingRate": "0.00010000",
    "markPrice": "331.00000000"
  },
  {
    "symbol": "AAVEUSDT",
    "fundingTime": 1755187200000,
    "fundingRate": "0.00010000",
    "markPrice": "315.45070833"
  },
  {
    "symbol": "AAVEUSDT",
    "fundingTime": 1755216000000,
    "fundingRate": "0.00002013",
    "markPrice": "312.40000000"
  },
  {
    "symbol": "AAVEUSDT",
    "fundingTime": 1755244800000,
    "fundingRate": "0.00000676",
    "markPrice": "310.85371354"
  },
  {
    "symbol": "AAVEUSDT",
    "fundingTime": 1755273600000,
    "fundingRate": "0.00008620",
    "markPrice": "295.19134375"
  },
  {
    "symbol": "AAVEUSDT",
    "fundingTime": 1755302400004,
    "fundingRate": "0.00005280",
    "markPrice": "299.82241332"
  },
  {
    "symbol": "AAVEUSDT",
    "fundingTime": 1755331200000,
    "fundingRate": "0.00006779",
    "markPrice": "298.81313462"
  },
  {
    "symbol": "AAVEUSDT",
    "fundingTime": 1755360000002,
    "fundingRate": "0.00005367",
    "markPrice": "293.35000000"
  },
  {
    "symbol": "AAVEUSDT",
    "fundingTime": 1755388800000,
    "fundingRate": "0.00003873",
    "markPrice": "295.47000000"
  },
  {
    "symbol": "AAVEUSDT",
    "fundingTime": 1755417600001,
    "fundingRate": "0.00005975",
    "markPrice": "301.20000000"
  },
  {
    "symbol": "AAVEUSDT",
    "fundingTime": 1755446400007,
    "fundingRate": "0.00003180",
    "markPrice": "310.15625000"
  },
  {
    "symbol": "AAVEUSDT",
    "fundingTime": 1755475200000,
    "fundingRate": "0.00002355",
    "markPrice": "303.01000000"
  },
  {
    "symbol": "AAVEUSDT",
    "fundingTime": 1755504000001,
    "fundingRate": "-0.00001017",
    "markPrice": "286.21000000"
  },
  {
    "symbol": "AAVEUSDT",
    "fundingTime": 1755532800002,
    "fundingRate": "-0.00000017",
    "markPrice": "290.18758854"
  },
  {
    "symbol": "AAVEUSDT",
    "fundingTime": 1755561600000,
    "fundingRate": "0.00006715",
    "markPrice": "288.48000000"
  },
  {
    "symbol": "AAVEUSDT",
    "fundingTime": 1755590400001,
    "fundingRate": "0.00004526",
    "markPrice": "283.50000000"
  },
  {
    "symbol": "AAVEUSDT",
    "fundingTime": 1755619200000,
    "fundingRate": "0.00002359",
    "markPrice": "280.50659375"
  },
  {
    "symbol": "AAVEUSDT",
    "fundingTime": 1755648000000,
    "fundingRate": "0.00002899",
    "markPrice": "277.25000000"
  },
  {
    "symbol": "AAVEUSDT",
    "fundingTime": 1755676800000,
    "fundingRate": "-0.00003552",
    "markPrice": "287.55000000"
  },
  {
    "symbol": "AAVEUSDT",
    "fundingTime": 1755705600000,
    "fundingRate": "0.00004535",
    "markPrice": "289.74000000"
  },
  {
    "symbol": "AAVEUSDT",
    "fundingTime": 1755734400006,
    "fundingRate": "-0.00000228",
    "markPrice": "299.20000000"
  },
  {
    "symbol": "AAVEUSDT",
    "fundingTime": 1755763200000,
    "fundingRate": "0.00009738",
    "markPrice": "301.73000000"
  },
  {
    "symbol": "AAVEUSDT",
    "fundingTime": 1755792000003,
    "fundingRate": "0.00007370",
    "markPrice": "297.11000000"
  },
  {
    "symbol": "AAVEUSDT",
    "fundingTime": 1755820800010,
    "fundingRate": "0.00010000",
    "markPrice": "299.94000000"
  },
  {
    "symbol": "AAVEUSDT",
    "fundingTime": 1755849600007,
    "fundingRate": "-0.00007277",
    "markPrice": "303.48438030"
  },
  {
    "symbol": "AAVEUSDT",
    "fundingTime": 1755878400001,
    "fundingRate": "0.00010000",
    "markPrice": "319.62659375"
  },
  {
    "symbol": "AAVEUSDT",
    "fundingTime": 1755907200004,
    "fundingRate": "0.00010000",
    "markPrice": "345.76300000"
  },
  {
    "symbol": "AAVEUSDT",
    "fundingTime": 1755936000006,
    "fundingRate": "0.00010000",
    "markPrice": "343.05343750"
  },
  {
    "symbol": "AAVEUSDT",
    "fundingTime": 1755964800000,
    "fundingRate": "0.00010000",
    "markPrice": "361.90593750"
  },
  {
    "symbol": "AAVEUSDT",
    "fundingTime": 1755993600001,
    "fundingRate": "0.00010000",
    "markPrice": "357.78843750"
  },
  {
    "symbol": "AAVEUSDT",
    "fundingTime": 1756022400002,
    "fundingRate": "0.00010000",
    "markPrice": "347.61000000"
  },
  {
    "symbol": "AAVEUSDT",
    "fundingTime": 1756051200001,
    "fundingRate": "0.00010000",
    "markPrice": "351.72500000"
  },
  {
    "symbol": "AAVEUSDT",
    "fundingTime": 1756080000000,
    "fundingRate": "0.00010000",
    "markPrice": "348.75357812"
  },
  {
    "symbol": "AAVEUSDT",
    "fundingTime": 1756108800002,
    "fundingRate": "0.00010000",
    "markPrice": "329.82000000"
  },
  {
    "symbol": "AAVEUSDT",
    "fundingTime": 1756137600002,
    "fundingRate": "0.00010000",
    "markPrice": "325.63407292"
  },
  {
    "symbol": "AAVEUSDT",
    "fundingTime": 1756166400000,
    "fundingRate": "0.00010000",
    "markPrice": "318.38077604"
  },
  {
    "symbol": "AAVEUSDT",
    "fundingTime": 1756195200000,
    "fundingRate": "0.00010000",
    "markPrice": "328.26000000"
  },
  {
    "symbol": "AAVEUSDT",
    "fundingTime": 1756224000000,
    "fundingRate": "0.00007137",
    "markPrice": "327.60251042"
  },
  {
    "symbol": "AAVEUSDT",
    "fundingTime": 1756252800003,
    "fundingRate": "-0.00000855",
    "markPrice": "335.59000000"
  },
  {
    "symbol": "AAVEUSDT",
    "fundingTime": 1756281600000,
    "fundingRate": "0.00009074",
    "markPrice": "329.89000000"
  },
  {
    "symbol": "AAVEUSDT",
    "fundingTime": 1756310400009,
    "fundingRate": "0.00008982",
    "markPrice": "326.36000000"
  },
  {
    "symbol": "AAVEUSDT",
    "fundingTime": 1756339200000,
    "fundingRate": "0.00007193",
    "markPrice": "320.49000000"
  },
  {
    "symbol": "AAVEUSDT",
    "fundingTime": 1756368000005,
    "fundingRate": "0.00001269",
    "markPrice": "325.91000000"
  },
  {
    "symbol": "AAVEUSDT",
    "fundingTime": 1756396800004,
    "fundingRate": "0.00006265",
    "markPrice": "316.14000000"
  },
  {
    "symbol": "AAVEUSDT",
    "fundingTime": 1756425600000,
    "fundingRate": "-0.00000115",
    "markPrice": "317.39233854"
  },
  {
    "symbol": "AAVEUSDT",
    "fundingTime": 1756454400000,
    "fundingRate": "0.00007543",
    "markPrice": "306.56000000"
  },
  {
    "symbol": "AAVEUSDT",
    "fundingTime": 1756483200005,
    "fundingRate": "0.00007471",
    "markPrice": "311.78000000"
  },
  {
    "symbol": "AAVEUSDT",
    "fundingTime": 1756512000000,
    "fundingRate": "-0.00005849",
    "markPrice": "319.03643750"
  },
  {
    "symbol": "AAVEUSDT",
    "fundingTime": 1756540800002,
    "fundingRate": "0.00002657",
    "markPrice": "316.80000000"
  },
  {
    "symbol": "AAVEUSDT",
    "fundingTime": 1756569600003,
    "fundingRate": "0.00002203",
    "markPrice": "314.48000000"
  },
  {
    "symbol": "AAVEUSDT",
    "fundingTime": 1756598400016,
    "fundingRate": "-0.00000973",
    "markPrice": "319.18000000"
  },
  {
    "symbol": "AAVEUSDT",
    "fundingTime": 1756627200000,
    "fundingRate": "0.00002203",
    "markPrice": "320.77484896"
  },
  {
    "symbol": "AAVEUSDT",
    "fundingTime": 1756656000001,
    "fundingRate": "-0.00000895",
    "markPrice": "319.97000000"
  },
  {
    "symbol": "AAVEUSDT",
    "fundingTime": 1756684800000,
    "fundingRate": "0.00002758",
    "markPrice": "315.58000000"
  },
  {
    "symbol": "AAVEUSDT",
    "fundingTime": 1756713600000,
    "fundingRate": "0.00006381",
    "markPrice": "316.31406250"
  },
  {
    "symbol": "AAVEUSDT",
    "fundingTime": 1756742400001,
    "fundingRate": "0.00001465",
    "markPrice": "306.71650000"
  },
  {
    "symbol": "AAVEUSDT",
    "fundingTime": 1756771200000,
    "fundingRate": "0.00000436",
    "markPrice": "304.68000000"
  },
  {
    "symbol": "AAVEUSDT",
    "fundingTime": 1756800000005,
    "fundingRate": "0.00004596",
    "markPrice": "310.98209375"
  },
  {
    "symbol": "AAVEUSDT",
    "fundingTime": 1756828800007,
    "fundingRate": "0.00006959",
    "markPrice": "308.96000000"
  },
  {
    "symbol": "AAVEUSDT",
    "fundingTime": 1756857600006,
    "fundingRate": "0.00010000",
    "markPrice": "315.53000000"
  },
  {
    "symbol": "AAVEUSDT",
    "fundingTime": 1756886400002,
    "fundingRate": "0.00003508",
    "markPrice": "315.45122881"
  },
  {
    "symbol": "AAVEUSDT",
    "fundingTime": 1756915200002,
    "fundingRate": "0.00002699",
    "markPrice": "325.36063021"
  },
  {
    "symbol": "AAVEUSDT",
    "fundingTime": 1756944000002,
    "fundingRate": "0.00007374",
    "markPrice": "327.73785417"
  },
  {
    "symbol": "AAVEUSDT",
    "fundingTime": 1756972800000,
    "fundingRate": "0.00006821",
    "markPrice": "317.70000000"
  },
  {
    "symbol": "AAVEUSDT",
    "fundingTime": 1757001600000,
    "fundingRate": "0.00008447",
    "markPrice": "308.64513021"
  },
  {
    "symbol": "AAVEUSDT",
    "fundingTime": 1757030400001,
    "fundingRate": "-0.00000528",
    "markPrice": "306.35000000"
  },
  {
    "symbol": "AAVEUSDT",
    "fundingTime": 1757059200006,
    "fundingRate": "0.00005095",
    "markPrice": "311.20842161"
  },
  {
    "symbol": "AAVEUSDT",
    "fundingTime": 1757088000000,
    "fundingRate": "-0.00001933",
    "markPrice": "301.54000000"
  },
  {
    "symbol": "AAVEUSDT",
    "fundingTime": 1757116800000,
    "fundingRate": "0.00010000",
    "markPrice": "302.18000000"
  },
  {
    "symbol": "AAVEUSDT",
    "fundingTime": 1757145600005,
    "fundingRate": "0.00002807",
    "markPrice": "301.95000000"
  },
  {
    "symbol": "AAVEUSDT",
    "fundingTime": 1757174400000,
    "fundingRate": "0.00006262",
    "markPrice": "298.69871822"
  },
  {
    "symbol": "AAVEUSDT",
    "fundingTime": 1757203200000,
    "fundingRate": "0.00010000",
    "markPrice": "298.19000000"
  },
  {
    "symbol": "AAVEUSDT",
    "fundingTime": 1757232000000,
    "fundingRate": "0.00003113",
    "markPrice": "301.40000000"
  },
  {
    "symbol": "AAVEUSDT",
    "fundingTime": 1757260800000,
    "fundingRate": "0.00001261",
    "markPrice": "299.67061458"
  },
  {
    "symbol": "AAVEUSDT",
    "fundingTime": 1757289600007,
    "fundingRate": "0.00002156",
    "markPrice": "301.38736229"
  },
  {
    "symbol": "AAVEUSDT",
    "fundingTime": 1757318400000,
    "fundingRate": "0.00010000",
    "markPrice": "299.53000000"
  },
  {
    "symbol": "AAVEUSDT",
    "fundingTime": 1757347200000,
    "fundingRate": "0.00008876",
    "markPrice": "306.19000000"
  },
  {
    "symbol": "AAVEUSDT",
    "fundingTime": 1757376000000,
    "fundingRate": "-0.00003156",
    "markPrice": "302.81000000"
  }
]