[
  {
    "symbol": "NKNUSDT",
    "fundingTime": 1754510400000,
    "fundingRate": "0.00005000",
    "markPrice": "0.02731193"
  },
  {
    "symbol": "NKNUSDT",
    "fundingTime": 1754524800003,
    "fundingRate": "0.00005000",
    "markPrice": "0.02710602"
  },
  {
    "symbol": "NKNUSDT",
    "fundingTime": 1754539200004,
    "fundingRate": "0.00005000",
    "markPrice": "0.02690682"
  },
  {
    "symbol": "NKNUSDT",
    "fundingTime": 1754553600002,
    "fundingRate": "0.00005000",
    "markPrice": "0.02728000"
  },
  {
    "symbol": "NKNUSDT",
    "fundingTime": 1754568000001,
    "fundingRate": "0.00005000",
    "markPrice": "0.02821818"
  },
  {
    "symbol": "NKNUSDT",
    "fundingTime": 1754582400002,
    "fundingRate": "0.00005000",
    "markPrice": "0.02802000"
  },
  {
    "symbol": "NKNUSDT",
    "fundingTime": 1754596800001,
    "fundingRate": "0.00005000",
    "markPrice": "0.02825000"
  },
  {
    "symbol": "NKNUSDT",
    "fundingTime": 1754611200002,
    "fundingRate": "0.00005000",
    "markPrice": "0.02848731"
  },
  {
    "symbol": "NKNUSDT",
    "fundingTime": 1754625600010,
    "fundingRate": "0.00005000",
    "markPrice": "0.02843871"
  },
  {
    "symbol": "NKNUSDT",
    "fundingTime": 1754640000004,
    "fundingRate": "0.00005000",
    "markPrice": "0.02867355"
  },
  {
    "symbol": "NKNUSDT",
    "fundingTime": 1754654400003,
    "fundingRate": "0.00005000",
    "markPrice": "0.02882819"
  },
  {
    "symbol": "NKNUSDT",
    "fundingTime": 1754668800000,
    "fundingRate": "0.00005000",
    "markPrice": "0.02847243"
  },
  {
    "symbol": "NKNUSDT",
    "fundingTime": 1754683200004,
    "fundingRate": "0.00005000",
    "markPrice": "0.02930901"
  },
  {
    "symbol": "NKNUSDT",
    "fundingTime": 1754697600005,
    "fundingRate": "0.00005000",
    "markPrice": "0.02922000"
  },
  {
    "symbol": "NKNUSDT",
    "fundingTime": 1754712000015,
    "fundingRate": "0.00005000",
    "markPrice": "0.02907290"
  },
  {
    "symbol": "NKNUSDT",
    "fundingTime": 1754726400000,
    "fundingRate": "0.00005290",
    "markPrice": "0.03009000"
  },
  {
    "symbol": "NKNUSDT",
    "fundingTime": 1754740800003,
    "fundingRate": "0.00005000",
    "markPrice": "0.02994000"
  },
  {
    "symbol": "NKNUSDT",
    "fundingTime": 1754755200007,
    "fundingRate": "0.00005000",
    "markPrice": "0.03003129"
  },
  {
    "symbol": "NKNUSDT",
    "fundingTime": 1754769600000,
    "fundingRate": "0.00005000",
    "markPrice": "0.02999000"
  },
  {
    "symbol": "NKNUSDT",
    "fundingTime": 1754784000003,
    "fundingRate": "0.00005000",
    "markPrice": "0.02983527"
  },
  {
    "symbol": "NKNUSDT",
    "fundingTime": 1754798400006,
    "fundingRate": "0.00005000",
    "markPrice": "0.03006000"
  },
  {
    "symbol": "NKNUSDT",
    "fundingTime": 1754812800005,
    "fundingRate": "0.00005000",
    "markPrice": "0.02918927"
  },
  {
    "symbol": "NKNUSDT",
    "fundingTime": 1754827200006,
    "fundingRate": "0.00005000",
    "markPrice": "0.02911870"
  },
  {
    "symbol": "NKNUSDT",
    "fundingTime": 1754841600002,
    "fundingRate": "0.00005000",
    "markPrice": "0.02925000"
  },
  {
    "symbol": "NKNUSDT",
    "fundingTime": 1754856000000,
    "fundingRate": "0.00005000",
    "markPrice": "0.02956653"
  },
  {
    "symbol": "NKNUSDT",
    "fundingTime": 1754870400000,
    "fundingRate": "0.00005000",
    "markPrice": "0.02924848"
  },
  {
    "symbol": "NKNUSDT",
    "fundingTime": 1754884800000,
    "fundingRate": "0.00005000",
    "markPrice": "0.02991419"
  },
  {
    "symbol": "NKNUSDT",
    "fundingTime": 1754899200000,
    "fundingRate": "0.00005000",
    "markPrice": "0.02901243"
  },
  {
    "symbol": "NKNUSDT",
    "fundingTime": 1754913600000,
    "fundingRate": "0.00005000",
    "markPrice": "0.02782297"
  },
  {
    "symbol": "NKNUSDT",
    "fundingTime": 1754928000000,
    "fundingRate": "0.00005000",
    "markPrice": "0.02853859"
  },
  {
    "symbol": "NKNUSDT",
    "fundingTime": 1754942400000,
    "fundingRate": "0.00005000",
    "markPrice": "0.02844046"
  },
  {
    "symbol": "NKNUSDT",
    "fundingTime": 1754956800000,
    "fundingRate": "0.00005000",
    "markPrice": "0.02725732"
  },
  {
    "symbol": "NKNUSDT",
    "fundingTime": 1754971200001,
    "fundingRate": "0.00005000",
    "markPrice": "0.02752355"
  },
  {
    "symbol": "NKNUSDT",
    "fundingTime": 1754985600001,
    "fundingRate": "0.00005000",
    "markPrice": "0.02767323"
  },
  {
    "symbol": "NKNUSDT",
    "fundingTime": 1755000000000,
    "fundingRate": "0.00005000",
    "markPrice": "0.02734871"
  },
  {
    "symbol": "NKNUSDT",
    "fundingTime": 1755014400005,
    "fundingRate": "0.00005000",
    "markPrice": "0.02927510"
  },
  {
    "symbol": "NKNUSDT",
    "fundingTime": 1755028800000,
    "fundingRate": "0.00005000",
    "markPrice": "0.02985076"
  },
  {
    "symbol": "NKNUSDT",
    "fundingTime": 1755043200000,
    "fundingRate": "0.00005000",
    "markPrice": "0.03020000"
  },
  {
    "symbol": "NKNUSDT",
    "fundingTime": 1755057600000,
    "fundingRate": "0.00005000",
    "markPrice": "0.03033909"
  },
  {
    "symbol": "NKNUSDT",
    "fundingTime": 1755072000002,
    "fundingRate": "0.00009762",
    "markPrice": "0.03013581"
  },
  {
    "symbol": "NKNUSDT",
    "fundingTime": 1755086400000,
    "fundingRate": "0.00009185",
    "markPrice": "0.03042933"
  },
  {
    "symbol": "NKNUSDT",
    "fundingTime": 1755100800006,
    "fundingRate": "0.00005362",
    "markPrice": "0.03045776"
  },
  {
    "symbol": "NKNUSDT",
    "fundingTime": 1755115200001,
    "fundingRate": "0.00005000",
    "markPrice": "0.03074634"
  },
  {
    "symbol": "NKNUSDT",
    "fundingTime": 1755129600002,
    "fundingRate": "0.00005000",
    "markPrice": "0.03069504"
  },
  {
    "symbol": "NKNUSDT",
    "fundingTime": 1755144000009,
    "fundingRate": "0.00007756",
    "markPrice": "0.03116427"
  },
  {
    "symbol": "NKNUSDT",
    "fundingTime": 1755158400003,
    "fundingRate": "0.00005000",
    "markPrice": "0.03035000"
  },
  {
    "symbol": "NKNUSDT",
    "fundingTime": 1755172800001,
    "fundingRate": "0.00005000",
    "markPrice": "0.02985713"
  },
  {
    "symbol": "NKNUSDT",
    "fundingTime": 1755187200000,
    "fundingRate": "0.00005000",
    "markPrice": "0.02820000"
  },
  {
    "symbol": "NKNUSDT",
    "fundingTime": 1755201600002,
    "fundingRate": "0.00005000",
    "markPrice": "0.02724000"
  },
  {
    "symbol": "NKNUSDT",
    "fundingTime": 1755216000000,
    "fundingRate": "0.00005000",
    "markPrice": "0.02718810"
  },
  {
    "symbol": "NKNUSDT",
    "fundingTime": 1755230400000,
    "fundingRate": "0.00005000",
    "markPrice": "0.02811101"
  },
  {
    "symbol": "NKNUSDT",
    "fundingTime": 1755244800000,
    "fundingRate": "0.00005000",
    "markPrice": "0.02831482"
  },
  {
    "symbol": "NKNUSDT",
    "fundingTime": 1755259200001,
    "fundingRate": "0.00005000",
    "markPrice": "0.02810000"
  },
  {
    "symbol": "NKNUSDT",
    "fundingTime": 1755273600000,
    "fundingRate": "0.00005000",
    "markPrice": "0.02706410"
  },
  {
    "symbol": "NKNUSDT",
    "fundingTime": 1755288000007,
    "fundingRate": "0.00005000",
    "markPrice": "0.02694000"
  },
  {
    "symbol": "NKNUSDT",
    "fundingTime": 1755302400004,
    "fundingRate": "0.00005000",
    "markPrice": "0.02752483"
  },
  {
    "symbol": "NKNUSDT",
    "fundingTime": 1755316800000,
    "fundingRate": "0.00005000",
    "markPrice": "0.02777017"
  },
  {
    "symbol": "NKNUSDT",
    "fundingTime": 1755331200000,
    "fundingRate": "0.00005000",
    "markPrice": "0.02783659"
  },
  {
    "symbol": "NKNUSDT",
    "fundingTime": 1755345600004,
    "fundingRate": "0.00005000",
    "markPrice": "0.02799000"
  },
  {
    "symbol": "NKNUSDT",
    "fundingTime": 1755360000002,
    "fundingRate": "0.00005000",
    "markPrice": "0.02915000"
  },
  {
    "symbol": "NKNUSDT",
    "fundingTime": 1755374400006,
    "fundingRate": "0.00005000",
    "markPrice": "0.02896598"
  },
  {
    "symbol": "NKNUSDT",
    "fundingTime": 1755388800000,
    "fundingRate": "0.00005000",
    "markPrice": "0.02903051"
  },
  {
    "symbol": "NKNUSDT",
    "fundingTime": 1755403200000,
    "fundingRate": "0.00005000",
    "markPrice": "0.02927919"
  },
  {
    "symbol": "NKNUSDT",
    "fundingTime": 1755417600001,
    "fundingRate": "0.00005000",
    "markPrice": "0.02935000"
  },
  {
    "symbol": "NKNUSDT",
    "fundingTime": 1755432000002,
    "fundingRate": "0.00005000",
    "markPrice": "0.02919000"
  },
  {
    "symbol": "NKNUSDT",
    "fundingTime": 1755446400007,
    "fundingRate": "0.00005000",
    "markPrice": "0.02950796"
  },
  {
    "symbol": "NKNUSDT",
    "fundingTime": 1755460800001,
    "fundingRate": "0.00005000",
    "markPrice": "0.02872516"
  },
  {
    "symbol": "NKNUSDT",
    "fundingTime": 1755475200000,
    "fundingRate": "0.00005000",
    "markPrice": "0.02881000"
  },
  {
    "symbol": "NKNUSDT",
    "fundingTime": 1755489600010,
    "fundingRate": "0.00005000",
    "markPrice": "0.02727650"
  },
  {
    "symbol": "NKNUSDT",
    "fundingTime": 1755504000001,
    "fundingRate": "0.00005000",
    "markPrice": "0.02696530"
  },
  {
    "symbol": "NKNUSDT",
    "fundingTime": 1755518400002,
    "fundingRate": "0.00005000",
    "markPrice": "0.02713229"
  },
  {
    "symbol": "NKNUSDT",
    "fundingTime": 1755532800002,
    "fundingRate": "0.00005000",
    "markPrice": "0.02752214"
  },
  {
    "symbol": "NKNUSDT",
    "fundingTime": 1755547200007,
    "fundingRate": "0.00005000",
    "markPrice": "0.02743240"
  },
  {
    "symbol": "NKNUSDT",
    "fundingTime": 1755561600000,
    "fundingRate": "0.00005000",
    "markPrice": "0.02736065"
  },
  {
    "symbol": "NKNUSDT",
    "fundingTime": 1755576000000,
    "fundingRate": "0.00005000",
    "markPrice": "0.02695484"
  },
  {
    "symbol": "NKNUSDT",
    "fundingTime": 1755590400001,
    "fundingRate": "0.00005000",
    "markPrice": "0.02705961"
  },
  {
    "symbol": "NKNUSDT",
    "fundingTime": 1755604800001,
    "fundingRate": "0.00005000",
    "markPrice": "0.02822000"
  },
  {
    "symbol": "NKNUSDT",
    "fundingTime": 1755619200000,
    "fundingRate": "0.00005000",
    "markPrice": "0.02735825"
  },
  {
    "symbol": "NKNUSDT",
    "fundingTime": 1755633600000,
    "fundingRate": "0.00005000",
    "markPrice": "0.02657000"
  },
  {
    "symbol": "NKNUSDT",
    "fundingTime": 1755648000000,
    "fundingRate": "0.00005000",
    "markPrice": "0.02629161"
  },
  {
    "symbol": "NKNUSDT",
    "fundingTime": 1755662400000,
    "fundingRate": "0.00005000",
    "markPrice": "0.02709271"
  },
  {
    "symbol": "NKNUSDT",
    "fundingTime": 1755676800000,
    "fundingRate": "0.00005000",
    "markPrice": "0.02742673"
  },
  {
    "symbol": "NKNUSDT",
    "fundingTime": 1755691200002,
    "fundingRate": "0.00005000",
    "markPrice": "0.02761037"
  },
  {
    "symbol": "NKNUSDT",
    "fundingTime": 1755705600000,
    "fundingRate": "0.00005000",
    "markPrice": "0.02805000"
  },
  {
    "symbol": "NKNUSDT",
    "fundingTime": 1755720000001,
    "fundingRate": "0.00005000",
    "markPrice": "0.02845806"
  },
  {
    "symbol": "NKNUSDT",
    "fundingTime": 1755734400006,
    "fundingRate": "0.00005000",
    "markPrice": "0.02851000"
  },
  {
    "symbol": "NKNUSDT",
    "fundingTime": 1755748800003,
    "fundingRate": "0.00005000",
    "markPrice": "0.02871220"
  },
  {
    "symbol": "NKNUSDT",
    "fundingTime": 1755763200000,
    "fundingRate": "0.00005000",
    "markPrice": "0.02854176"
  },
  {
    "symbol": "NKNUSDT",
    "fundingTime": 1755777600009,
    "fundingRate": "0.00005000",
    "markPrice": "0.02796000"
  },
  {
    "symbol": "NKNUSDT",
    "fundingTime": 1755792000003,
    "fundingRate": "0.00005000",
    "markPrice": "0.02752774"
  },
  {
    "symbol": "NKNUSDT",
    "fundingTime": 1755806400000,
    "fundingRate": "0.00005000",
    "markPrice": "0.02753323"
  },
  {
    "symbol": "NKNUSDT",
    "fundingTime": 1755820800010,
    "fundingRate": "0.00005000",
    "markPrice": "0.02751416"
  },
  {
    "symbol": "NKNUSDT",
    "fundingTime": 1755835200003,
    "fundingRate": "0.00005000",
    "markPrice": "0.02762522"
  },
  {
    "symbol": "NKNUSDT",
    "fundingTime": 1755849600007,
    "fundingRate": "0.00005000",
    "markPrice": "0.02788000"
  },
  {
    "symbol": "NKNUSDT",
    "fundingTime": 1755864000001,
    "fundingRate": "0.00005000",
    "markPrice": "0.02675290"
  },
  {
    "symbol": "NKNUSDT",
    "fundingTime": 1755878400001,
    "fundingRate": "0.00005000",
    "markPrice": "0.02917245"
  },
  {
    "symbol": "NKNUSDT",
    "fundingTime": 1755892800004,
    "fundingRate": "0.00005000",
    "markPrice": "0.03022000"
  },
  {
    "symbol": "NKNUSDT",
    "fundingTime": 1755907200004,
    "fundingRate": "0.00007147",
    "markPrice": "0.03029551"
  },
  {
    "symbol": "NKNUSDT",
    "fundingTime": 1755921600000,
    "fundingRate": "0.00005000",
    "markPrice": "0.02964238"
  },
  {
    "symbol": "NKNUSDT",
    "fundingTime": 1755936000006,
    "fundingRate": "0.00005000",
    "markPrice": "0.02960000"
  },
  {
    "symbol": "NKNUSDT",
    "fundingTime": 1755950400000,
    "fundingRate": "0.00005000",
    "markPrice": "0.02965314"
  },
  {
    "symbol": "NKNUSDT",
    "fundingTime": 1755964800000,
    "fundingRate": "0.00005000",
    "markPrice": "0.02960702"
  },
  {
    "symbol": "NKNUSDT",
    "fundingTime": 1755979200005,
    "fundingRate": "0.00005000",
    "markPrice": "0.02976166"
  },
  {
    "symbol": "NKNUSDT",
    "fundingTime": 1755993600001,
    "fundingRate": "0.00005000",
    "markPrice": "0.02969000"
  },
  {
    "symbol": "NKNUSDT",
    "fundingTime": 1756008000000,
    "fundingRate": "0.00005000",
    "markPrice": "0.02928548"
  },
  {
    "symbol": "NKNUSDT",
    "fundingTime": 1756022400002,
    "fundingRate": "0.00005000",
    "markPrice": "0.02876000"
  },
  {
    "symbol": "NKNUSDT",
    "fundingTime": 1756036800003,
    "fundingRate": "0.00005000",
    "markPrice": "0.02862895"
  },
  {
    "symbol": "NKNUSDT",
    "fundingTime": 1756051200001,
    "fundingRate": "0.00005000",
    "markPrice": "0.02877000"
  },
  {
    "symbol": "NKNUSDT",
    "fundingTime": 1756065600008,
    "fundingRate": "0.00005000",
    "markPrice": "0.02925000"
  },
  {
    "symbol": "NKNUSDT",
    "fundingTime": 1756080000000,
    "fundingRate": "0.00005000",
    "markPrice": "0.02901744"
  },
  {
    "symbol": "NKNUSDT",
    "fundingTime": 1756094400001,
    "fundingRate": "0.00005000",
    "markPrice": "0.02911903"
  },
  {
    "symbol": "NKNUSDT",
    "fundingTime": 1756108800002,
    "fundingRate": "0.00005000",
    "markPrice": "0.02742000"
  },
  {
    "symbol": "NKNUSDT",
    "fundingTime": 1756123200000,
    "fundingRate": "0.00005000",
    "markPrice": "0.02715001"
  },
  {
    "symbol": "NKNUSDT",
    "fundingTime": 1756137600002,
    "fundingRate": "0.00005000",
    "markPrice": "0.02700785"
  },
  {
    "symbol": "NKNUSDT",
    "fundingTime": 1756152000003,
    "fundingRate": "0.00005000",
    "markPrice": "0.02604738"
  },
  {
    "symbol": "NKNUSDT",
    "fundingTime": 1756166400000,
    "fundingRate": "0.00005000",
    "markPrice": "0.02601000"
  },
  {
    "symbol": "NKNUSDT",
    "fundingTime": 1756180800007,
    "fundingRate": "0.00005000",
    "markPrice": "0.02613758"
  },
  {
    "symbol": "NKNUSDT",
    "fundingTime": 1756195200000,
    "fundingRate": "-0.00000152",
    "markPrice": "0.02649086"
  },
  {
    "symbol": "NKNUSDT",
    "fundingTime": 1756209600001,
    "fundingRate": "0.00005000",
    "markPrice": "0.02637641"
  },
  {
    "symbol": "NKNUSDT",
    "fundingTime": 1756224000000,
    "fundingRate": "0.00005000",
    "markPrice": "0.02681839"
  },
  {
    "symbol": "NKNUSDT",
    "fundingTime": 1756238400000,
    "fundingRate": "0.00005000",
    "markPrice": "0.02763398"
  },
  {
    "symbol": "NKNUSDT",
    "fundingTime": 1756252800003,
    "fundingRate": "0.00005000",
    "markPrice": "0.02784701"
  },
  {
    "symbol": "NKNUSDT",
    "fundingTime": 1756267200000,
    "fundingRate": "-0.00005593",
    "markPrice": "0.02772000"
  },
  {
    "symbol": "NKNUSDT",
    "fundingTime": 1756281600000,
    "fundingRate": "0.00005000",
    "markPrice": "0.02733867"
  },
  {
    "symbol": "NKNUSDT",
    "fundingTime": 1756296000003,
    "fundingRate": "0.00005000",
    "markPrice": "0.02773222"
  },
  {
    "symbol": "NKNUSDT",
    "fundingTime": 1756310400009,
    "fundingRate": "0.00005000",
    "markPrice": "0.02825233"
  },
  {
    "symbol": "NKNUSDT",
    "fundingTime": 1756324800001,
    "fundingRate": "0.00005000",
    "markPrice": "0.02794797"
  },
  {
    "symbol": "NKNUSDT",
    "fundingTime": 1756339200000,
    "fundingRate": "0.00005000",
    "markPrice": "0.02793877"
  },
  {
    "symbol": "NKNUSDT",
    "fundingTime": 1756353600000,
    "fundingRate": "0.00005000",
    "markPrice": "0.02838711"
  },
  {
    "symbol": "NKNUSDT",
    "fundingTime": 1756368000005,
    "fundingRate": "0.00005000",
    "markPrice": "0.02871493"
  },
  {
    "symbol": "NKNUSDT",
    "fundingTime": 1756382400000,
    "fundingRate": "0.00005000",
    "markPrice": "0.02847070"
  },
  {
    "symbol": "NKNUSDT",
    "fundingTime": 1756396800004,
    "fundingRate": "0.00005000",
    "markPrice": "0.02836000"
  },
  {
    "symbol": "NKNUSDT",
    "fundingTime": 1756411200003,
    "fundingRate": "0.00005000",
    "markPrice": "0.02786562"
  },
  {
    "symbol": "NKNUSDT",
    "fundingTime": 1756425600000,
    "fundingRate": "0.00005000",
    "markPrice": "0.02874000"
  },
  {
    "symbol": "NKNUSDT",
    "fundingTime": 1756440000008,
    "fundingRate": "0.00005000",
    "markPrice": "0.02854000"
  },
  {
    "symbol": "NKNUSDT",
    "fundingTime": 1756454400000,
    "fundingRate": "0.00005000",
    "markPrice": "0.02704065"
  },
  {
    "symbol": "NKNUSDT",
    "fundingTime": 1756468800010,
    "fundingRate": "0.00005000",
    "markPrice": "0.02637460"
  },
  {
    "symbol": "NKNUSDT",
    "fundingTime": 1756483200005,
    "fundingRate": "0.00005000",
    "markPrice": "0.02652779"
  },
  {
    "symbol": "NKNUSDT",
    "fundingTime": 1756497600000,
    "fundingRate": "0.00005000",
    "markPrice": "0.02623000"
  },
  {
    "symbol": "NKNUSDT",
    "fundingTime": 1756512000000,
    "fundingRate": "0.00005000",
    "markPrice": "0.02663000"
  },
  {
    "symbol": "NKNUSDT",
    "fundingTime": 1756526400000,
    "fundingRate": "0.00005000",
    "markPrice": "0.02743364"
  },
  {
    "symbol": "NKNUSDT",
    "fundingTime": 1756540800002,
    "fundingRate": "0.00005000",
    "markPrice": "0.02763465"
  },
  {
    "symbol": "NKNUSDT",
    "fundingTime": 1756555200006,
    "fundingRate": "0.00005000",
    "markPrice": "0.02786399"
  },
  {
    "symbol": "NKNUSDT",
    "fundingTime": 1756569600003,
    "fundingRate": "0.00005000",
    "markPrice": "0.02770000"
  },
  {
    "symbol": "NKNUSDT",
    "fundingTime": 1756584000000,
    "fundingRate": "0.00005000",
    "markPrice": "0.02737000"
  },
  {
    "symbol": "NKNUSDT",
    "fundingTime": 1756598400016,
    "fundingRate": "0.00005000",
    "markPrice": "0.02747632"
  },
  {
    "symbol": "NKNUSDT",
    "fundingTime": 1756612800000,
    "fundingRate": "0.00005000",
    "markPrice": "0.02812506"
  },
  {
    "symbol": "NKNUSDT",
    "fundingTime": 1756627200000,
    "fundingRate": "0.00005000",
    "markPrice": "0.02742950"
  },
  {
    "symbol": "NKNUSDT",
    "fundingTime": 1756641600003,
    "fundingRate": "0.00005000",
    "markPrice": "0.02734000"
  },
  {
    "symbol": "NKNUSDT",
    "fundingTime": 1756656000001,
    "fundingRate": "0.00005000",
    "markPrice": "0.02695081"
  },
  {
    "symbol": "NKNUSDT",
    "fundingTime": 1756670400000,
    "fundingRate": "0.00005000",
    "markPrice": "0.02691773"
  },
  {
    "symbol": "NKNUSDT",
    "fundingTime": 1756684800000,
    "fundingRate": "0.00005000",
    "markPrice": "0.02601544"
  },
  {
    "symbol": "NKNUSDT",
    "fundingTime": 1756699200005,
    "fundingRate": "0.00005000",
    "markPrice": "0.02577224"
  },
  {
    "symbol": "NKNUSDT",
    "fundingTime": 1756713600000,
    "fundingRate": "0.00005000",
    "markPrice": "0.02648295"
  },
  {
    "symbol": "NKNUSDT",
    "fundingTime": 1756728000014,
    "fundingRate": "0.00005000",
    "markPrice": "0.02606000"
  },
  {
    "symbol": "NKNUSDT",
    "fundingTime": 1756742400001,
    "fundingRate": "0.00005000",
    "markPrice": "0.02564000"
  },
  {
    "symbol": "NKNUSDT",
    "fundingTime": 1756756800008,
    "fundingRate": "0.00005000",
    "markPrice": "0.02585755"
  },
  {
    "symbol": "NKNUSDT",
    "fundingTime": 1756771200000,
    "fundingRate": "0.00005000",
    "markPrice": "0.02567032"
  },
  {
    "symbol": "NKNUSDT",
    "fundingTime": 1756785600009,
    "fundingRate": "0.00005000",
    "markPrice": "0.02643000"
  },
  {
    "symbol": "NKNUSDT",
    "fundingTime": 1756800000005,
    "fundingRate": "0.00005000",
    "markPrice": "0.02600523"
  },
  {
    "symbol": "NKNUSDT",
    "fundingTime": 1756814400003,
    "fundingRate": "0.00005000",
    "markPrice": "0.02613000"
  },
  {
    "symbol": "NKNUSDT",
    "fundingTime": 1756828800007,
    "fundingRate": "0.00005000",
    "markPrice": "0.02580164"
  },
  {
    "symbol": "NKNUSDT",
    "fundingTime": 1756843200001,
    "fundingRate": "0.00005000",
    "markPrice": "0.02615742"
  },
  {
    "symbol": "NKNUSDT",
    "fundingTime": 1756857600006,
    "fundingRate": "0.00005000",
    "markPrice": "0.02646783"
  },
  {
    "symbol": "NKNUSDT",
    "fundingTime": 1756872000003,
    "fundingRate": "0.00005000",
    "markPrice": "0.02631993"
  },
  {
    "symbol": "NKNUSDT",
    "fundingTime": 1756886400002,
    "fundingRate": "0.00005000",
    "markPrice": "0.02614491"
  },
  {
    "symbol": "NKNUSDT",
    "fundingTime": 1756900800000,
    "fundingRate": "0.00005000",
    "markPrice": "0.02624000"
  },
  {
    "symbol": "NKNUSDT",
    "fundingTime": 1756915200002,
    "fundingRate": "0.00005000",
    "markPrice": "0.02671000"
  },
  {
    "symbol": "NKNUSDT",
    "fundingTime": 1756929600006,
    "fundingRate": "0.00005000",
    "markPrice": "0.02669000"
  },
  {
    "symbol": "NKNUSDT",
    "fundingTime": 1756944000002,
    "fundingRate": "0.00005000",
    "markPrice": "0.02636308"
  },
  {
    "symbol": "NKNUSDT",
    "fundingTime": 1756958400000,
    "fundingRate": "0.00005000",
    "markPrice": "0.02584000"
  },
  {
    "symbol": "NKNUSDT",
    "fundingTime": 1756972800000,
    "fundingRate": "0.00005000",
    "markPrice": "0.02546000"
  },
  {
    "symbol": "NKNUSDT",
    "fundingTime": 1756987200002,
    "fundingRate": "0.00005000",
    "markPrice": "0.02566200"
  },
  {
    "symbol": "NKNUSDT",
    "fundingTime": 1757001600000,
    "fundingRate": "0.00005000",
    "markPrice": "0.02542000"
  },
  {
    "symbol": "NKNUSDT",
    "fundingTime": 1757016000000,
    "fundingRate": "0.00005000",
    "markPrice": "0.02512000"
  },
  {
    "symbol": "NKNUSDT",
    "fundingTime": 1757030400001,
    "fundingRate": "0.00005000",
    "markPrice": "0.02529223"
  },
  {
    "symbol": "NKNUSDT",
    "fundingTime": 1757044800000,
    "fundingRate": "0.00005000",
    "markPrice": "0.02567000"
  },
  {
    "symbol": "NKNUSDT",
    "fundingTime": 1757059200006,
    "fundingRate": "0.00005000",
    "markPrice": "0.02619000"
  },
  {
    "symbol": "NKNUSDT",
    "fundingTime": 1757073600001,
    "fundingRate": "0.00005000",
    "markPrice": "0.02591396"
  },
  {
    "symbol": "NKNUSDT",
    "fundingTime": 1757088000000,
    "fundingRate": "0.00005000",
    "markPrice": "0.02544000"
  },
  {
    "symbol": "NKNUSDT",
    "fundingTime": 1757102400000,
    "fundingRate": "0.00005000",
    "markPrice": "0.02576000"
  },
  {
    "symbol": "NKNUSDT",
    "fundingTime": 1757116800000,
    "fundingRate": "0.00005000",
    "markPrice": "0.02589438"
  },
  {
    "symbol": "NKNUSDT",
    "fundingTime": 1757131200000,
    "fundingRate": "0.00005000",
    "markPrice": "0.02598000"
  },
  {
    "symbol": "NKNUSDT",
    "fundingTime": 1757145600005,
    "fundingRate": "0.00005000",
    "markPrice": "0.02573179"
  },
  {
    "symbol": "NKNUSDT",
    "fundingTime": 1757160000000,
    "fundingRate": "0.00005000",
    "markPrice": "0.02573956"
  },
  {
    "symbol": "NKNUSDT",
    "fundingTime": 1757174400000,
    "fundingRate": "0.00005000",
    "markPrice": "0.02562419"
  },
  {
    "symbol": "NKNUSDT",
    "fundingTime": 1757188800001,
    "fundingRate": "0.00005000",
    "markPrice": "0.02551838"
  },
  {
    "symbol": "NKNUSDT",
    "fundingTime": 1757203200000,
    "fundingRate": "0.00005000",
    "markPrice": "0.02581000"
  },
  {
    "symbol": "NKNUSDT",
    "fundingTime": 1757217600008,
    "fundingRate": "0.00005000",
    "markPrice": "0.02641619"
  },
  {
    "symbol": "NKNUSDT",
    "fundingTime": 1757232000000,
    "fundingRate": "0.00005000",
    "markPrice": "0.02625211"
  },
  {
    "symbol": "NKNUSDT",
    "fundingTime": 1757246400000,
    "fundingRate": "0.00015096",
    "markPrice": "0.02636078"
  },
  {
    "symbol": "NKNUSDT",
    "fundingTime": 1757260800000,
    "fundingRate": "0.00005000",
    "markPrice": "0.02619284"
  },
  {
    "symbol": "NKNUSDT",
    "fundingTime": 1757275200003,
    "fundingRate": "0.00005000",
    "markPrice": "0.02606144"
  },
  {
    "symbol": "NKNUSDT",
    "fundingTime": 1757289600007,
    "fundingRate": "0.00005000",
    "markPrice": "0.02635797"
  },
  {
    "symbol": "NKNUSDT",
    "fundingTime": 1757304000008,
    "fundingRate": "0.00005000",
    "markPrice": "0.02652464"
  },
  {
    "symbol": "NKNUSDT",
    "fundingTime": 1757318400000,
    "fundingRate": "0.00005000",
    "markPrice": "0.02635481"
  },
  {
    "symbol": "NKNUSDT",
    "fundingTime": 1757332800005,
    "fundingRate": "0.00005000",
    "markPrice": "0.02669614"
  },
  {
    "symbol": "NKNUSDT",
    "fundingTime": 1757347200000,
    "fundingRate": "0.00005000",
    "markPrice": "0.02713000"
  },
  {
    "symbol": "NKNUSDT",
    "fundingTime": 1757361600001,
    "fundingRate": "0.00005000",
    "markPrice": "0.02682290"
  },
  {
    "symbol": "NKNUSDT",
    "fundingTime": 1757376000000,
    "fundingRate": "0.00005000",
    "markPrice": "0.02692000"
  }
]